{
  "repo": "openclaw/openclaw",
  "cluster_id": "pr-inventory-needs_proof-20260615T054135-055",
  "mode": "plan",
  "run_id": "27526633752",
  "run_url": "https://github.com/openclaw/clownfish/actions/runs/27526633752",
  "head_sha": "dd092f08dfed6ec600221eb169e0ce317c148af7",
  "workflow_conclusion": "success",
  "workflow_status": "completed",
  "workflow_created_at": "2026-06-15T05:46:53Z",
  "workflow_updated_at": "2026-06-15T05:49:40Z",
  "result_status": "planned",
  "source_job": "jobs/openclaw/inbox/pr-inventory-needs_proof-20260615T054135-055.md",
  "published_at": "2026-06-15T05:53:32.923Z",
  "canonical": null,
  "canonical_issue": null,
  "canonical_pr": null,
  "summary": "Plan-mode PR inventory classification only. No shared canonical was selected. Security-sensitive PRs are routed to central security handling; closed PRs are kept closed; remaining open non-security PRs are kept independent because they are not duplicate closeout candidates and are not merge/fix eligible in this job.",
  "actions": [
    {
      "target": "#68283",
      "action": "keep_independent",
      "status": "planned",
      "classification": "independent",
      "canonical": null,
      "candidate_fix": null,
      "reason": "Open non-security PR with unique scope; keep independently for proof/review rather than closing or merging."
    },
    {
      "target": "#68127",
      "action": "keep_independent",
      "status": "planned",
      "classification": "independent",
      "canonical": null,
      "candidate_fix": null,
      "reason": "Useful narrow PR but still needs proof/test follow-up; no closure basis."
    },
    {
      "target": "#66442",
      "action": "keep_closed",
      "status": "skipped",
      "classification": null,
      "canonical": null,
      "candidate_fix": null,
      "reason": "Already closed; no mutation is valid in plan mode."
    },
    {
      "target": "#68129",
      "action": "route_security",
      "status": "planned",
      "classification": "security_sensitive",
      "canonical": null,
      "candidate_fix": null,
      "reason": "Quarantine this PR only; continue unrelated non-security classifications."
    },
    {
      "target": "#67836",
      "action": "route_security",
      "status": "planned",
      "classification": "security_sensitive",
      "canonical": null,
      "candidate_fix": null,
      "reason": "Quarantine this PR only; broad memory/runtime boundary work is outside backlog cleanup mutation."
    },
    {
      "target": "#67460",
      "action": "route_security",
      "status": "planned",
      "classification": "security_sensitive",
      "canonical": null,
      "candidate_fix": null,
      "reason": "Security-sensitive candidate is quarantined even though already closed; no ProjectClownfish mutation should be planned."
    },
    {
      "target": "#66098",
      "action": "keep_independent",
      "status": "planned",
      "classification": "independent",
      "canonical": null,
      "candidate_fix": null,
      "reason": "Open useful PR with unique scope; keep independently for proof and review resolution."
    },
    {
      "target": "#68986",
      "action": "keep_independent",
      "status": "planned",
      "classification": "independent",
      "canonical": null,
      "candidate_fix": null,
      "reason": "Draft PR with unresolved review findings; keep independently rather than close or merge."
    },
    {
      "target": "#67727",
      "action": "keep_independent",
      "status": "planned",
      "classification": "independent",
      "canonical": null,
      "candidate_fix": null,
      "reason": "Open feature/config PR with deferred wiring and failed proof; keep independently."
    },
    {
      "target": "#70156",
      "action": "route_security",
      "status": "planned",
      "classification": "security_sensitive",
      "canonical": null,
      "candidate_fix": null,
      "reason": "Quarantine this exec-surface/security-boundary PR; no backlog cleanup mutation is appropriate."
    }
  ],
  "action_counts": {
    "keep_independent": 5,
    "keep_closed": 1,
    "route_security": 4
  },
  "action_status_counts": {
    "planned": 9,
    "skipped": 1
  },
  "fix_counts": {},
  "apply_counts": {},
  "needs_human": [],
  "fix_actions": [],
  "apply_actions": []
}
