{
  "repo": "openclaw/openclaw",
  "cluster_id": "gitcrawl-63-bulk-plan-20260615-a",
  "mode": "plan",
  "run_id": "27521531737",
  "run_url": "https://github.com/openclaw/clownfish/actions/runs/27521531737",
  "head_sha": "c7fde105fe4b1bf849faf5ed130f10118614c64c",
  "workflow_conclusion": "success",
  "workflow_status": "completed",
  "workflow_created_at": "2026-06-15T03:06:11Z",
  "workflow_updated_at": "2026-06-15T03:08:09Z",
  "result_status": "planned",
  "source_job": "jobs/openclaw/inbox/gitcrawl-63-bulk-plan-20260615-a.md",
  "published_at": "2026-06-15T03:58:15.023Z",
  "canonical": "#84012",
  "canonical_issue": "#84012",
  "canonical_pr": null,
  "summary": "Plan-only classification for the eight job-provided cluster refs. #84012 remains the best live canonical for the broad status hang report. #74185 and #83560 are exact job security-signal refs and are routed to central security handling; unrelated non-security status/configure/config hang items are kept related rather than closed because the hydrated evidence shows multiple subpaths, unique platform or command scopes, and no landed canonical fix.",
  "actions": [
    {
      "target": "#74085",
      "action": "keep_closed",
      "status": "skipped",
      "classification": "related",
      "canonical": "#84012",
      "candidate_fix": null,
      "reason": "Already closed in live preflight state; keep as related historical context only."
    },
    {
      "target": "#74185",
      "action": "route_security",
      "status": "planned",
      "classification": "security_sensitive",
      "canonical": null,
      "candidate_fix": null,
      "reason": "Exact job security-signal ref; route only this item to central security handling and do not classify it as a merge or close candidate."
    },
    {
      "target": "#83560",
      "action": "route_security",
      "status": "planned",
      "classification": "security_sensitive",
      "canonical": null,
      "candidate_fix": null,
      "reason": "Exact job security-signal ref; quarantine this issue without closing or using it as a non-security duplicate target."
    },
    {
      "target": "#83862",
      "action": "keep_related",
      "status": "planned",
      "classification": "related",
      "canonical": "#84012",
      "candidate_fix": null,
      "reason": "Related configure/onboard fix candidate, but not a duplicate of the status canonical and not mergeable or closeable in this plan."
    },
    {
      "target": "#84001",
      "action": "keep_related",
      "status": "planned",
      "classification": "related",
      "canonical": "#84012",
      "candidate_fix": null,
      "reason": "Same status hang family as #84012, but Windows-specific behavior and `status --all` contrast should remain visible."
    },
    {
      "target": "#84012",
      "action": "keep_canonical",
      "status": "planned",
      "classification": "canonical",
      "canonical": "#84012",
      "candidate_fix": null,
      "reason": "Best live canonical for the broad unresolved status hang family."
    },
    {
      "target": "#84698",
      "action": "keep_related",
      "status": "planned",
      "classification": "related",
      "canonical": "#84012",
      "candidate_fix": null,
      "reason": "Related status hang report with useful regression details; keep open with #84012 as the canonical family anchor."
    },
    {
      "target": "#85002",
      "action": "keep_related",
      "status": "planned",
      "classification": "related",
      "canonical": "#84012",
      "candidate_fix": null,
      "reason": "Related gateway/config hang family member, but distinct command surface and suspected path; do not collapse into the status canonical."
    }
  ],
  "action_counts": {
    "keep_closed": 1,
    "route_security": 2,
    "keep_related": 4,
    "keep_canonical": 1
  },
  "action_status_counts": {
    "skipped": 1,
    "planned": 7
  },
  "fix_counts": {},
  "apply_counts": {},
  "needs_human": [],
  "fix_actions": [],
  "apply_actions": []
}
