{
  "repo": "openclaw/openclaw",
  "cluster_id": "pr-inventory-mixed-20260615T143135-106",
  "mode": "plan",
  "run_id": "27554572903",
  "run_url": "https://github.com/openclaw/clownfish/actions/runs/27554572903",
  "head_sha": "874a85e75dbe919d3363a334a753aa7108b147bd",
  "workflow_conclusion": "success",
  "workflow_status": "completed",
  "workflow_created_at": "2026-06-15T14:47:13Z",
  "workflow_updated_at": "2026-06-15T14:48:53Z",
  "result_status": "needs_human",
  "source_job": "jobs/openclaw/inbox/pr-inventory-mixed-20260615T143135-106.md",
  "published_at": "2026-06-15T14:54:21.547Z",
  "canonical": null,
  "canonical_issue": null,
  "canonical_pr": null,
  "summary": "Plan-only PR inventory classification for 25 listed refs. No GitHub mutations are planned. The hydrated artifact reported no security-sensitive refs; all open PRs with live state are kept as independent or related inventory items. #89559 is the only blocked item because live kind/state/updated_at were unavailable.",
  "actions": [
    {
      "target": "#89172",
      "action": "keep_independent",
      "status": "planned",
      "classification": "independent",
      "canonical": null,
      "candidate_fix": null,
      "reason": "Distinct Feishu voice-duration fix; no duplicate/supersession evidence in this inventory shard."
    },
    {
      "target": "#89395",
      "action": "keep_related",
      "status": "planned",
      "classification": "related",
      "canonical": null,
      "candidate_fix": null,
      "reason": "Related Feishu SecretRef/media work, but not proven duplicate or safely superseded."
    },
    {
      "target": "#89404",
      "action": "keep_related",
      "status": "planned",
      "classification": "related",
      "canonical": null,
      "candidate_fix": null,
      "reason": "Draft maintainer-owned hardening PR in a related family; no closure action is safe."
    },
    {
      "target": "#89409",
      "action": "keep_independent",
      "status": "planned",
      "classification": "independent",
      "canonical": null,
      "candidate_fix": null,
      "reason": "Independent docs clarification; dirty merge state blocks merge but not inventory classification."
    },
    {
      "target": "#89416",
      "action": "keep_independent",
      "status": "planned",
      "classification": "independent",
      "canonical": null,
      "candidate_fix": null,
      "reason": "Independent browser availability bugfix; failing check prevents any merge/fixed-by closeout planning."
    },
    {
      "target": "#89419",
      "action": "keep_related",
      "status": "planned",
      "classification": "related",
      "canonical": null,
      "candidate_fix": null,
      "reason": "Related to #89490; no canonical chosen in this inventory shard."
    },
    {
      "target": "#89422",
      "action": "keep_independent",
      "status": "planned",
      "classification": "independent",
      "canonical": null,
      "candidate_fix": null,
      "reason": "Independent plugin diagnostics PR; missing checks only warrants conservative keep."
    },
    {
      "target": "#89437",
      "action": "keep_related",
      "status": "planned",
      "classification": "related",
      "canonical": null,
      "candidate_fix": null,
      "reason": "Related Google/provider tool-schema hardening; not a duplicate closeout candidate."
    },
    {
      "target": "#89442",
      "action": "keep_independent",
      "status": "planned",
      "classification": "independent",
      "canonical": null,
      "candidate_fix": null,
      "reason": "Independent Codex startup availability fix; no overlap requiring closure."
    },
    {
      "target": "#89451",
      "action": "keep_related",
      "status": "planned",
      "classification": "related",
      "canonical": null,
      "candidate_fix": null,
      "reason": "Related Google tool-schema hardening; no safe supersession decision."
    },
    {
      "target": "#89454",
      "action": "keep_related",
      "status": "planned",
      "classification": "related",
      "canonical": null,
      "candidate_fix": null,
      "reason": "Related Feishu SecretRef/media work with broader credential-resolution scope."
    },
    {
      "target": "#89468",
      "action": "keep_related",
      "status": "planned",
      "classification": "related",
      "canonical": null,
      "candidate_fix": null,
      "reason": "Related hardening PR; keep open for maintainer-owned draft path."
    },
    {
      "target": "#77017",
      "action": "keep_independent",
      "status": "planned",
      "classification": "independent",
      "canonical": null,
      "candidate_fix": null,
      "reason": "Broad independent UI/gateway feature PR; dirty state and missing checks block any stronger recommendation."
    },
    {
      "target": "#89482",
      "action": "keep_independent",
      "status": "planned",
      "classification": "independent",
      "canonical": null,
      "candidate_fix": null,
      "reason": "Independent Discord route-resolution bugfix; no duplicate evidence."
    },
    {
      "target": "#89490",
      "action": "keep_related",
      "status": "planned",
      "classification": "related",
      "canonical": null,
      "candidate_fix": null,
      "reason": "Related to #89419; no closure action planned."
    },
    {
      "target": "#89499",
      "action": "keep_related",
      "status": "planned",
      "classification": "related",
      "canonical": null,
      "candidate_fix": null,
      "reason": "Related diagnostic-hardening PR; not a duplicate closeout candidate."
    },
    {
      "target": "#89504",
      "action": "keep_related",
      "status": "planned",
      "classification": "related",
      "canonical": null,
      "candidate_fix": null,
      "reason": "Related inventory hardening PR; keep open."
    },
    {
      "target": "#89513",
      "action": "keep_related",
      "status": "planned",
      "classification": "related",
      "canonical": null,
      "candidate_fix": null,
      "reason": "Related agents session hardening PR; no safe supersession decision."
    },
    {
      "target": "#89526",
      "action": "keep_independent",
      "status": "planned",
      "classification": "independent",
      "canonical": null,
      "candidate_fix": null,
      "reason": "Independent gateway/config reload PR; enrichment gaps block stronger action but not classification."
    },
    {
      "target": "#89529",
      "action": "keep_related",
      "status": "planned",
      "classification": "related",
      "canonical": null,
      "candidate_fix": null,
      "reason": "Related provider schema hardening PR; keep open."
    },
    {
      "target": "#89533",
      "action": "keep_independent",
      "status": "planned",
      "classification": "independent",
      "canonical": null,
      "candidate_fix": null,
      "reason": "Independent docs PR with sufficient live state for non-mutating inventory classification."
    },
    {
      "target": "#89538",
      "action": "keep_independent",
      "status": "planned",
      "classification": "independent",
      "canonical": null,
      "candidate_fix": null,
      "reason": "Independent sessions/gateway cleanup PR; proof/check gaps mean keep only."
    },
    {
      "target": "#89547",
      "action": "keep_independent",
      "status": "planned",
      "classification": "independent",
      "canonical": null,
      "candidate_fix": null,
      "reason": "Independent Telegram feature/behavior PR; no closure or merge recommendation planned."
    },
    {
      "target": "#89558",
      "action": "keep_independent",
      "status": "planned",
      "classification": "independent",
      "canonical": null,
      "candidate_fix": null,
      "reason": "Independent docs PR; keep open."
    },
    {
      "target": "#89559",
      "action": "needs_human",
      "status": "blocked",
      "classification": "needs_human",
      "canonical": null,
      "candidate_fix": null,
      "reason": "Live state is unavailable for this listed candidate, so no reliable non-mutating PR classification beyond needs_human is safe."
    }
  ],
  "action_counts": {
    "keep_independent": 12,
    "keep_related": 12,
    "needs_human": 1
  },
  "action_status_counts": {
    "planned": 24,
    "blocked": 1
  },
  "fix_counts": {},
  "apply_counts": {},
  "needs_human": [
    "#89559: live kind/state/updated_at unavailable in the preflight artifact, so the worker cannot satisfy the required target_kind/target_updated_at fields for a normal PR classification."
  ],
  "fix_actions": [],
  "apply_actions": []
}
