{
  "repo": "openclaw/openclaw",
  "cluster_id": "pr-inventory-ready_for_maintainer-20260615T223445-086",
  "mode": "plan",
  "run_id": "27580942551-1-86",
  "workflow_run_id": "27580942551",
  "run_attempt": "1",
  "matrix_index": "86",
  "run_url": "https://github.com/openclaw/clownfish/actions/runs/27580942551",
  "head_sha": "11023f07de225364eeb7bd9fd8705f16da575f9c",
  "workflow_conclusion": "failure",
  "workflow_status": "completed",
  "workflow_created_at": "2026-06-15T22:36:11Z",
  "workflow_updated_at": "2026-06-15T22:40:56Z",
  "result_status": "planned",
  "source_job": "jobs/openclaw/inbox/pr-inventory-ready_for_maintainer-20260615T223445-086.md",
  "published_at": "2026-06-16T19:01:33.504Z",
  "canonical": null,
  "canonical_issue": null,
  "canonical_pr": null,
  "summary": "Plan-only PR inventory classification. This shard has no shared canonical; merge, fix, raise_pr, and low-signal closeout are blocked by job permissions, so hydrated non-security PRs are classified independently and non-mutating. Two validator-identified security-sensitive refs are quarantined with route_security. Four candidate refs were not present in the compacted hydrated item matrix, so those specific refs need a fresh preflight before classification.",
  "actions": [
    {
      "target": "#90223",
      "action": "keep_independent",
      "status": "planned",
      "classification": "independent",
      "canonical": null,
      "candidate_fix": null,
      "reason": "Independent ready-for-maintainer PR; no duplicate, superseded, low-signal, or security signal in hydrated artifact."
    },
    {
      "target": "#90226",
      "action": "keep_independent",
      "status": "planned",
      "classification": "independent",
      "canonical": null,
      "candidate_fix": null,
      "reason": "Independent behavior-change PR requiring maintainer/product review outside this cleanup shard."
    },
    {
      "target": "#90230",
      "action": "keep_independent",
      "status": "planned",
      "classification": "independent",
      "canonical": null,
      "candidate_fix": null,
      "reason": "Independent test PR; not eligible for closeout or merge in this plan."
    },
    {
      "target": "#93038",
      "action": "needs_human",
      "status": "planned",
      "classification": "needs_human",
      "canonical": null,
      "candidate_fix": null,
      "reason": "Fresh hydrated live state is needed before classifying this PR."
    },
    {
      "target": "#90273",
      "action": "keep_independent",
      "status": "planned",
      "classification": "independent",
      "canonical": null,
      "candidate_fix": null,
      "reason": "Independent test PR with author-followup/proof blocker; no closure basis."
    },
    {
      "target": "#90280",
      "action": "keep_independent",
      "status": "planned",
      "classification": "independent",
      "canonical": null,
      "candidate_fix": null,
      "reason": "Independent channel test PR; no duplicate or superseded evidence."
    },
    {
      "target": "#90300",
      "action": "keep_independent",
      "status": "planned",
      "classification": "independent",
      "canonical": null,
      "candidate_fix": null,
      "reason": "Independent focused fix PR awaiting maintainer review."
    },
    {
      "target": "#90328",
      "action": "keep_independent",
      "status": "planned",
      "classification": "independent",
      "canonical": null,
      "candidate_fix": null,
      "reason": "Independent multi-surface feature/compatibility PR; maintainer review is the right next step, not cleanup closure."
    },
    {
      "target": "#90331",
      "action": "route_security",
      "status": "planned",
      "classification": "security_sensitive",
      "canonical": null,
      "candidate_fix": null,
      "reason": "Security-sensitive trust-boundary hardening must be routed to central security handling instead of ProjectClownfish backlog cleanup."
    },
    {
      "target": "#90357",
      "action": "keep_independent",
      "status": "planned",
      "classification": "independent",
      "canonical": null,
      "candidate_fix": null,
      "reason": "Independent provider/alias bugfix with proof blocker; not closable as duplicate or low-signal."
    },
    {
      "target": "#90363",
      "action": "keep_independent",
      "status": "planned",
      "classification": "independent",
      "canonical": null,
      "candidate_fix": null,
      "reason": "Independent small CI/test maintenance PR."
    },
    {
      "target": "#90373",
      "action": "keep_independent",
      "status": "planned",
      "classification": "independent",
      "canonical": null,
      "candidate_fix": null,
      "reason": "Independent larger gateway compatibility PR requiring maintainer review."
    },
    {
      "target": "#90421",
      "action": "keep_independent",
      "status": "planned",
      "classification": "independent",
      "canonical": null,
      "candidate_fix": null,
      "reason": "Independent session-state PR; not a cleanup close candidate."
    },
    {
      "target": "#90433",
      "action": "keep_independent",
      "status": "planned",
      "classification": "independent",
      "canonical": null,
      "candidate_fix": null,
      "reason": "Independent memory-core fix PR awaiting maintainer review."
    },
    {
      "target": "#92251",
      "action": "needs_human",
      "status": "planned",
      "classification": "needs_human",
      "canonical": null,
      "candidate_fix": null,
      "reason": "Fresh hydrated live state is needed before classifying this PR."
    },
    {
      "target": "#91310",
      "action": "keep_independent",
      "status": "planned",
      "classification": "independent",
      "canonical": null,
      "candidate_fix": null,
      "reason": "Independent provider compatibility fix with author-followup signal; not a cleanup close candidate."
    },
    {
      "target": "#91345",
      "action": "keep_independent",
      "status": "planned",
      "classification": "independent",
      "canonical": null,
      "candidate_fix": null,
      "reason": "Independent CLI UX PR awaiting maintainer review."
    },
    {
      "target": "#91346",
      "action": "route_security",
      "status": "planned",
      "classification": "security_sensitive",
      "canonical": null,
      "candidate_fix": null,
      "reason": "No-auth gateway warning changes touch security-sensitive exposure/auth posture and must be routed to central security handling."
    },
    {
      "target": "#91409",
      "action": "needs_human",
      "status": "planned",
      "classification": "needs_human",
      "canonical": null,
      "candidate_fix": null,
      "reason": "Fresh hydrated live state is needed before classifying this PR."
    },
    {
      "target": "#90271",
      "action": "keep_independent",
      "status": "planned",
      "classification": "independent",
      "canonical": null,
      "candidate_fix": null,
      "reason": "Independent test PR with proof/author-followup blocker; no closure basis."
    },
    {
      "target": "#93274",
      "action": "needs_human",
      "status": "planned",
      "classification": "needs_human",
      "canonical": null,
      "candidate_fix": null,
      "reason": "Fresh hydrated live state is needed before classifying this PR."
    },
    {
      "target": "#41284",
      "action": "keep_independent",
      "status": "planned",
      "classification": "independent",
      "canonical": null,
      "candidate_fix": null,
      "reason": "Independent contributor PR with unresolved proof/review context; no cleanup closure."
    },
    {
      "target": "#50463",
      "action": "keep_independent",
      "status": "planned",
      "classification": "independent",
      "canonical": null,
      "candidate_fix": null,
      "reason": "Independent agent UX fix with proof/review blockers; no closeout basis."
    },
    {
      "target": "#75403",
      "action": "keep_independent",
      "status": "planned",
      "classification": "independent",
      "canonical": null,
      "candidate_fix": null,
      "reason": "Independent bot-generated fix PR; not mergeable or closable by this plan."
    },
    {
      "target": "#75469",
      "action": "keep_independent",
      "status": "planned",
      "classification": "independent",
      "canonical": null,
      "candidate_fix": null,
      "reason": "Independent bot-generated fix PR requiring maintainer review; merge/fix actions are blocked by job policy."
    }
  ],
  "action_counts": {
    "keep_independent": 19,
    "needs_human": 4,
    "route_security": 2
  },
  "action_status_counts": {
    "planned": 25
  },
  "fix_counts": {},
  "apply_counts": {},
  "needs_human": [
    "#93038 requires fresh hydrated live state before classification because it is missing from the compacted preflight item matrix.",
    "#92251 requires fresh hydrated live state before classification because it is missing from the compacted preflight item matrix.",
    "#91409 requires fresh hydrated live state before classification because it is missing from the compacted preflight item matrix.",
    "#93274 requires fresh hydrated live state before classification because it is missing from the compacted preflight item matrix."
  ],
  "fix_actions": [],
  "apply_actions": []
}
