{
  "repo": "openclaw/openclaw",
  "cluster_id": "repair-94022-live-pr-inventory-20260617t082059-005-repair-wave-20260617",
  "mode": "autonomous",
  "run_id": "27718703487",
  "workflow_run_id": "27718703487",
  "run_attempt": "1",
  "matrix_index": null,
  "run_url": "https://github.com/openclaw/clownfish/actions/runs/27718703487",
  "head_sha": "6984812bb39f4746261cb868f55fb6a9b5c5ef74",
  "workflow_conclusion": "success",
  "workflow_status": "completed",
  "workflow_created_at": "2026-06-17T20:46:43Z",
  "workflow_updated_at": "2026-06-17T20:51:29Z",
  "result_status": "planned",
  "source_job": "jobs/openclaw/inbox/repair-94022-live-pr-inventory-20260617t082059-005-repair-wave-20260617.md",
  "published_at": "2026-06-17T20:52:31.436Z",
  "canonical": "https://github.com/openclaw/openclaw/pull/94022",
  "canonical_issue": "https://github.com/openclaw/openclaw/issues/93935",
  "canonical_pr": "https://github.com/openclaw/openclaw/pull/94022",
  "summary": "Current main still only carries startup overflow catch-up deferral ids as a transient skip set for the immediate start() maintenance pass. Other maintenance recompute callers still call without that skip, so #94022 is the canonical repair path but needs contributor-branch repair before any merge recommendation. No GitHub mutations are allowed by this job.",
  "actions": [
    {
      "target": "#94022",
      "action": "fix_needed",
      "status": "planned",
      "classification": "canonical",
      "canonical": "#94022",
      "candidate_fix": null,
      "reason": "Repair the editable contributor branch before any merge recommendation."
    },
    {
      "target": "cluster:repair-94022-live-pr-inventory-20260617t082059-005-repair-wave-20260617",
      "action": "build_fix_artifact",
      "status": "planned",
      "classification": null,
      "canonical": "#94022",
      "candidate_fix": null,
      "reason": "Executable repair artifact for the allowed fix lane."
    },
    {
      "target": "#93935",
      "action": "keep_canonical",
      "status": "planned",
      "classification": "canonical",
      "canonical": "#93935",
      "candidate_fix": "#94022",
      "reason": "Keep the canonical issue open until the repaired PR lands."
    },
    {
      "target": "#93810",
      "action": "keep_closed",
      "status": "skipped",
      "classification": "related",
      "canonical": "#93935",
      "candidate_fix": "#94022",
      "reason": "Closed historical related PR; evidence only."
    },
    {
      "target": "#81731",
      "action": "keep_related",
      "status": "planned",
      "classification": "related",
      "canonical": "#93935",
      "candidate_fix": null,
      "reason": "Related cron future-slot repair work, not a duplicate of the startup deferral state bug."
    },
    {
      "target": "#81691",
      "action": "keep_related",
      "status": "planned",
      "classification": "related",
      "canonical": "#93935",
      "candidate_fix": "#81731",
      "reason": "Related but independent root cause."
    },
    {
      "target": "#94017",
      "action": "keep_independent",
      "status": "planned",
      "classification": "independent",
      "canonical": null,
      "candidate_fix": null,
      "reason": "Separate provider/think issue cluster."
    },
    {
      "target": "#93835",
      "action": "keep_independent",
      "status": "planned",
      "classification": "independent",
      "canonical": null,
      "candidate_fix": "#94017",
      "reason": "Separate provider/think issue cluster."
    },
    {
      "target": "#78272",
      "action": "keep_closed",
      "status": "skipped",
      "classification": "related",
      "canonical": "#93935",
      "candidate_fix": null,
      "reason": "Closed historical related PR; evidence only."
    },
    {
      "target": "#90315",
      "action": "keep_closed",
      "status": "skipped",
      "classification": "independent",
      "canonical": null,
      "candidate_fix": "#91248",
      "reason": "Closed independent provider issue; evidence only."
    },
    {
      "target": "#91248",
      "action": "keep_closed",
      "status": "skipped",
      "classification": "independent",
      "canonical": null,
      "candidate_fix": null,
      "reason": "Closed independent provider PR; evidence only."
    }
  ],
  "action_counts": {
    "fix_needed": 1,
    "build_fix_artifact": 1,
    "keep_canonical": 1,
    "keep_closed": 4,
    "keep_related": 2,
    "keep_independent": 2
  },
  "action_status_counts": {
    "planned": 7,
    "skipped": 4
  },
  "fix_counts": {
    "blocked": 1
  },
  "apply_counts": {},
  "needs_human": [],
  "repair_candidate": {
    "target": "#94022",
    "source_refs": [
      "#94022",
      "#93935",
      "#93810",
      "#78272",
      "#81731",
      "#91248",
      "#94017",
      "#81691",
      "#90315",
      "#93835"
    ],
    "repair_strategy": "repair_contributor_branch",
    "planned_actions": [
      "fix_needed",
      "build_fix_artifact"
    ],
    "summary": "Repair #94022 on the contributor branch so startup overflow catch-up deferral ids become service state, not a one-call local skip set. All maintenance recompute callers should preserve those deferred ids until their staggered catch-up fires, is finalized, or is explicitly released/cleared.",
    "pr_title": "fix(cron): preserve startup catch-up deferrals across maintenance recomputes",
    "pr_body": "## Summary\nFixes #93935 by repairing #94022 so startup overflow catch-up deferral ids live in cron service state instead of only in the local `start()` maintenance call. This keeps read RPCs, finalize paths, empty-due timer maintenance, manual run preflight, and reservation release from advancing deferred catch-up runs to the next natural cron schedule before the staggered catch-up fires.\n\nCredit: based on #94022 by @Jah-xy. Prior related context from #93810 by @yetval.\n\n## Repair Notes\n- Add/keep a state-owned set of startup catch-up deferral job ids.\n- Have `recomputeNextRunsForMaintenance` consult that state for future cron repair skips in every caller, while preserving explicit caller options where useful.\n- Clear ids when the deferred job fires/finalizes, is released, is disabled/removed, or no longer has the deferred next-run shape.\n- Add regression coverage for read/list/status, finalize, empty-due timer maintenance, manual preflight, and reservation-release callers.\n\n## Verification\n- `node scripts/run-vitest.mjs src/cron/service.startup-overflow-clobber.test.ts src/cron/service.restart-catchup.test.ts src/cron/service/ops.test.ts src/cron/service/ops.regression.test.ts src/cron/service/timer.regression.test.ts src/cron/service/timer.test.ts src/cron/service.jobs.test.ts`\n- `pnpm check:changed`\n- `scripts/pr review-validate-artifacts 94022`",
    "likely_files": [
      "src/cron/service/state.ts",
      "src/cron/service/jobs.ts",
      "src/cron/service/ops.ts",
      "src/cron/service/timer.ts",
      "src/cron/service.startup-overflow-clobber.test.ts",
      "src/cron/service.restart-catchup.test.ts",
      "src/cron/service/ops.test.ts",
      "src/cron/service/ops.regression.test.ts",
      "src/cron/service/timer.regression.test.ts",
      "src/cron/service/timer.test.ts",
      "src/cron/service.jobs.test.ts"
    ],
    "validation_commands": [
      "node scripts/run-vitest.mjs src/cron/service.startup-overflow-clobber.test.ts src/cron/service.restart-catchup.test.ts src/cron/service/ops.test.ts src/cron/service/ops.regression.test.ts src/cron/service/timer.regression.test.ts src/cron/service/timer.test.ts src/cron/service.jobs.test.ts",
      "pnpm check:changed",
      "scripts/pr review-validate-artifacts 94022"
    ],
    "credit_notes": [
      "Credit @Jah-xy as the #94022 source PR author and preserve https://github.com/openclaw/openclaw/pull/94022 in the PR body/update summary.",
      "Mention #93810 by @yetval as the earlier startup-only deferral fix and regression context, not as the replacement source branch.",
      "The user-facing release-note context should say cron startup overflow catch-up deferrals now survive read/status/list, finalize, timer maintenance, manual preflight, and reservation-release recomputes before the staggered catch-up fires."
    ],
    "source_job": "jobs/openclaw/inbox/repair-94022-live-pr-inventory-20260617t082059-005-repair-wave-20260617.md",
    "security_sensitive": false,
    "security_routed_refs": [],
    "needs_human": [],
    "repair_status": null,
    "terminal": null
  },
  "fix_actions": [
    {
      "action": "execute_fix",
      "status": "blocked",
      "target": null,
      "pr": null,
      "branch": null,
      "source_action": null,
      "source_status": null,
      "repair_strategy": "repair_contributor_branch",
      "reason": "fix artifact is too broad for autonomous execution; split into narrower jobs or explicitly set CLOWNFISH_ALLOW_BROAD_FIX_ARTIFACTS=1",
      "commit": null,
      "checkpoint_commits": null,
      "retry_recommended": null,
      "recoverable_branch_pushed": null,
      "title": null,
      "url": null
    }
  ],
  "apply_actions": [],
  "apply_audit_actions": []
}
