{
  "repo": "openclaw/openclaw",
  "cluster_id": "live-pr-inventory-20260627T162216-002",
  "mode": "autonomous",
  "run_id": "28294890482",
  "workflow_run_id": "28294890482",
  "run_attempt": "1",
  "matrix_index": null,
  "run_url": "https://github.com/openclaw/clownfish/actions/runs/28294890482",
  "head_sha": "aab5023974dd43fa7680a43808045641358880bb",
  "workflow_conclusion": "success",
  "workflow_status": "completed",
  "workflow_created_at": "2026-06-27T16:23:24Z",
  "workflow_updated_at": "2026-06-27T16:25:57Z",
  "result_status": "blocked",
  "source_job": "jobs/openclaw/inbox/live-pr-inventory-20260627T162216-002.md",
  "published_at": "2026-06-27T16:26:32.157Z",
  "canonical": "https://github.com/openclaw/openclaw/pull/96587",
  "canonical_issue": "https://github.com/openclaw/openclaw/issues/55242",
  "canonical_pr": "https://github.com/openclaw/openclaw/pull/96587",
  "summary": "#96587 is the canonical open PR for the Feishu identity.emoji card-header bug tracked by #55242. It is small, clean, editable by maintainers, linked to the canonical issue, and has passing checks/proof in the hydrated artifact. Merge is blocked only on the external exact-head merge preflight and fresh Codex /review required by this shard.",
  "actions": [
    {
      "target": "#55242",
      "action": "keep_canonical",
      "status": "planned",
      "classification": "canonical",
      "canonical": "#55242",
      "candidate_fix": "#96587",
      "reason": "Canonical issue remains open until the candidate PR lands."
    },
    {
      "target": "#96587",
      "action": "merge_candidate",
      "status": "blocked",
      "classification": "canonical",
      "canonical": "#55242",
      "candidate_fix": "#96587",
      "reason": "external_merge_preflight_required"
    },
    {
      "target": "#92937",
      "action": "keep_closed",
      "status": "skipped",
      "classification": "superseded",
      "canonical": "#96587",
      "candidate_fix": "#96587",
      "reason": "Historical closed context only; no mutation planned."
    },
    {
      "target": "#93589",
      "action": "keep_closed",
      "status": "skipped",
      "classification": "superseded",
      "canonical": "#96587",
      "candidate_fix": "#96587",
      "reason": "Historical closed context only; no mutation planned."
    }
  ],
  "action_counts": {
    "keep_canonical": 1,
    "merge_candidate": 1,
    "keep_closed": 2
  },
  "action_status_counts": {
    "planned": 1,
    "blocked": 1,
    "skipped": 2
  },
  "fix_counts": {
    "skipped": 1
  },
  "apply_counts": {
    "skipped": 1
  },
  "needs_human": [],
  "repair_candidate": null,
  "fix_actions": [
    {
      "action": "execute_fix",
      "status": "skipped",
      "target": null,
      "pr": null,
      "branch": null,
      "source_action": null,
      "source_status": null,
      "repair_strategy": null,
      "reason": "worker result status blocked is not executable",
      "commit": null,
      "checkpoint_commits": null,
      "retry_recommended": null,
      "recoverable_branch_pushed": null,
      "title": null,
      "url": null
    }
  ],
  "apply_actions": [
    {
      "target": "#96587",
      "action": "merge_candidate",
      "status": "skipped",
      "classification": "canonical",
      "canonical": "#55242",
      "candidate_fix": "#96587",
      "title": null,
      "idempotency_key": "live-pr-inventory-20260627T162216-002:#96587:merge-candidate:7eca53c4096ddab773a67514d5fe1a876a6f3d80",
      "source_status": "blocked",
      "source_reason": "external_merge_preflight_required",
      "reason": "action status is blocked",
      "merged_at": null,
      "merge_commit_sha": null,
      "expected_head_sha": null,
      "live_state": null,
      "live_updated_at": null,
      "apply_attempt": 1,
      "applied_at": "2026-06-27T16:25:53.258Z",
      "report_source": "apply"
    }
  ],
  "apply_audit_actions": [
    {
      "target": "#96587",
      "action": "merge_candidate",
      "status": "skipped",
      "classification": "canonical",
      "canonical": "#55242",
      "candidate_fix": "#96587",
      "title": null,
      "idempotency_key": "live-pr-inventory-20260627T162216-002:#96587:merge-candidate:7eca53c4096ddab773a67514d5fe1a876a6f3d80",
      "source_status": "blocked",
      "source_reason": "external_merge_preflight_required",
      "reason": "action status is blocked",
      "merged_at": null,
      "merge_commit_sha": null,
      "expected_head_sha": null,
      "live_state": null,
      "live_updated_at": null,
      "apply_attempt": 1,
      "applied_at": "2026-06-27T16:25:53.258Z",
      "report_source": "apply"
    },
    {
      "target": "#96587",
      "action": "merge_candidate",
      "status": "skipped",
      "classification": "canonical",
      "canonical": "#55242",
      "candidate_fix": "#96587",
      "title": null,
      "idempotency_key": "live-pr-inventory-20260627T162216-002:#96587:merge-candidate:7eca53c4096ddab773a67514d5fe1a876a6f3d80",
      "source_status": "blocked",
      "source_reason": "external_merge_preflight_required",
      "reason": "action status is blocked",
      "merged_at": null,
      "merge_commit_sha": null,
      "expected_head_sha": null,
      "live_state": null,
      "live_updated_at": null,
      "apply_attempt": 2,
      "applied_at": "2026-06-27T16:25:53.582Z",
      "report_source": "apply"
    }
  ]
}
